climb_onyx_gui/__init__.py
climb_onyx_gui/_version.py
climb_onyx_gui/exceptions.py
climb_onyx_gui/handlers.py
climb_onyx_gui/validators.py
climb_onyx_gui-0.12.5.data/data/etc/jupyter/jupyter_server_config.d/climb_onyx_gui.json
climb_onyx_gui-0.12.5.data/data/share/jupyter/labextensions/climb-onyx-gui-extension/package.json
climb_onyx_gui-0.12.5.data/data/share/jupyter/labextensions/climb-onyx-gui-extension/static/150.f5d3cbd1df6a85087836.js
climb_onyx_gui-0.12.5.data/data/share/jupyter/labextensions/climb-onyx-gui-extension/static/821.7692b05630674a501734.js
climb_onyx_gui-0.12.5.data/data/share/jupyter/labextensions/climb-onyx-gui-extension/static/953.6f4057e483f0230bfdd4.js
climb_onyx_gui-0.12.5.data/data/share/jupyter/labextensions/climb-onyx-gui-extension/static/988.2edd70e9eb880bdcf6e9.js
climb_onyx_gui-0.12.5.data/data/share/jupyter/labextensions/climb-onyx-gui-extension/static/988.2edd70e9eb880bdcf6e9.js.LICENSE.txt
climb_onyx_gui-0.12.5.data/data/share/jupyter/labextensions/climb-onyx-gui-extension/static/remoteEntry.4924055af1c8215795a7.js
climb_onyx_gui-0.12.5.data/data/share/jupyter/labextensions/climb-onyx-gui-extension/static/style.js
climb_onyx_gui-0.12.5.data/data/share/jupyter/labextensions/climb-onyx-gui-extension/static/third-party-licenses.json
climb_onyx_gui-0.12.5.data/data/share/jupyter/labextensions/climb-onyx-gui-extension/install.json
climb_onyx_gui-0.12.5.dist-info/METADATA
climb_onyx_gui-0.12.5.dist-info/WHEEL
climb_onyx_gui-0.12.5.dist-info/licenses/LICENSE
climb_onyx_gui-0.12.5.dist-info/RECORD
